cocaddy/__init__.py
cocaddy-0.0.1a1.dist-info/METADATA
cocaddy-0.0.1a1.dist-info/WHEEL
cocaddy-0.0.1a1.dist-info/top_level.txt
cocaddy-0.0.1a1.dist-info/RECORD
