Metadata-Version: 2.1
Name: cocaddy
Version: 0.0.1a1
Summary: cotton candy instance python version
Home-page: https://github.com/misakicoca/cotton-instance
Author: MisakiCoca
Author-email: misakicoca@gmail.com
License: UNKNOWN
Project-URL: Bug Tracker, https://github.com/misakicoca/cotton-instance/issues
Platform: UNKNOWN
Classifier: Programming Language :: Python :: 3
Requires-Python: >=3.6
